Metadata-Version: 1.0
Name: GBprobability
Version: 0.1
Summary: Gaussian distributions
Home-page: UNKNOWN
Author: Tagne Nguifo Eric Hermann
Author-email: UNKNOWN
License: UNKNOWN
Platform: UNKNOWN
